retry/__init__.py
retry/api.py
retry/compat.py
retry/tests/__init__.py
retry/tests/test_retry.py
retry-0.9.1.dist-info/DESCRIPTION.rst
retry-0.9.1.dist-info/METADATA
retry-0.9.1.dist-info/metadata.json
retry-0.9.1.dist-info/pbr.json
retry-0.9.1.dist-info/RECORD
retry-0.9.1.dist-info/top_level.txt
retry-0.9.1.dist-info/WHEEL
