Metadata-Version: 2.0
Name: retry
Version: 0.9.1
Summary: Easy to use retry decorator.
Home-page: https://github.com/invl/retry
Author: invl
Author-email: invlpg@gmail.com
License: Apache License 2.0
Platform: UNKNOWN
Classifier: Development Status :: 4 - Beta
Classifier: Intended Audience :: Developers
Classifier: License :: OSI Approved :: Apache Software License
Classifier: Natural Language :: English
Classifier: Operating System :: OS Independent
Classifier: Programming Language :: Python
Classifier: Programming Language :: Python :: 2.6
Classifier: Programming Language :: Python :: 2.7
Classifier: Programming Language :: Python :: 3
Classifier: Programming Language :: Python :: 3.4
Classifier: Programming Language :: Python :: Implementation :: PyPy
Classifier: Topic :: Software Development
Requires-Dist: decorator (>=3.4.2,<4.0.0)
Requires-Dist: py (>=1.4.26,<2.0.0)
